snp_rest/__init__.py
snp_rest-0.0.6.dist-info/LICENSE
snp_rest-0.0.6.dist-info/METADATA
snp_rest-0.0.6.dist-info/WHEEL
snp_rest-0.0.6.dist-info/top_level.txt
snp_rest-0.0.6.dist-info/RECORD
