Metadata-Version: 2.1
Name: snp-rest
Version: 0.0.6
Summary: Simple REST interface to the Selenio Network Processor
Home-page: https://github.com/UndyingScroll
Author: Kevin Pulley
Author-email: kpulley@imaginecommunications.com
License: UNKNOWN
Platform: UNKNOWN
Classifier: Programming Language :: Python :: 3
Classifier: License :: OSI Approved :: MIT License
Classifier: Operating System :: OS Independent
Requires-Python: >=3.6
Requires-Dist: requests-ntlm
